mpsiemlib/__init__.py
mpsiemlib/common/BaseFunctions.py
mpsiemlib/common/Interfaces.py
mpsiemlib/common/MPSIEMAuth.py
mpsiemlib/common/__init__.py
mpsiemlib/helpers/__init__.py
mpsiemlib/helpers/content_helpers.py
mpsiemlib/modules/Assets.py
mpsiemlib/modules/Conveyor.py
mpsiemlib/modules/Events.py
mpsiemlib/modules/EventsAPI.py
mpsiemlib/modules/Filters.py
mpsiemlib/modules/HealthMonitor.py
mpsiemlib/modules/Incidents.py
mpsiemlib/modules/KnowledgeBase.py
mpsiemlib/modules/Macros.py
mpsiemlib/modules/SourceMonitor.py
mpsiemlib/modules/Tables.py
mpsiemlib/modules/Tasks.py
mpsiemlib/modules/UsersAndRoles.py
mpsiemlib/modules/__init__.py
mpsiemlib-1.6.1.dist-info/LICENSE
mpsiemlib-1.6.1.dist-info/METADATA
mpsiemlib-1.6.1.dist-info/WHEEL
mpsiemlib-1.6.1.dist-info/top_level.txt
mpsiemlib-1.6.1.dist-info/RECORD
