Metadata-Version: 2.1
Name: mpsiemlib
Version: 1.6.1
Summary: MaxPatrol SIEM API SDK
Home-page: https://github.com/GenRockeR/mpsiemlib
Author: nikolaiav
Author-email: 
Maintainer: GenRockeR
License: GPLv3
Requires-Python: >=3.7
License-File: LICENSE
Requires-Dist: requests
Requires-Dist: PyYAML
Requires-Dist: pytz
Requires-Dist: elasticsearch<8.0.0,>=7.10.0
